doubletdetection/__init__.py
doubletdetection/doubletdetection.py
doubletdetection/plot.py
doubletdetection-4.3.0.post1.dist-info/METADATA
doubletdetection-4.3.0.post1.dist-info/WHEEL
doubletdetection-4.3.0.post1.dist-info/licenses/LICENSE.txt
doubletdetection-4.3.0.post1.dist-info/RECORD
