Metadata-Version: 2.4
Name: doubletdetection
Version: 4.3.0.post1
Summary: Method to detect and enable removal of doublets from single-cell RNA-sequencing.
Project-URL: Documentation, https://doubletdetection.readthedocs.io/
Project-URL: Homepage, https://github.com/JonathanShor/DoubletDetection
Author: Ambrose Carr
Author-email: Adam Gayoso <adamgayoso@berkeley.edu>, Jonathan Shor <jonathan.shor@nyu.edu>
License: MIT
License-File: LICENSE.txt
Classifier: Development Status :: 4 - Beta
Classifier: Intended Audience :: Science/Research
Classifier: Natural Language :: English
Classifier: Operating System :: MacOS :: MacOS X
Classifier: Operating System :: Microsoft :: Windows
Classifier: Operating System :: POSIX :: Linux
Classifier: Programming Language :: Python :: 3.10
Classifier: Topic :: Scientific/Engineering :: Bio-Informatics
Requires-Python: >=3.10
Requires-Dist: anndata>=0.8
Requires-Dist: matplotlib>=3.6
Requires-Dist: numpy>=1.24
Requires-Dist: phenograph
Requires-Dist: scanpy>1.10.0
Requires-Dist: scipy>=1.8
Requires-Dist: tqdm
Provides-Extra: dev
Requires-Dist: black[jupyter]>=20.8b1; extra == 'dev'
Requires-Dist: flake8>=3.7.7; extra == 'dev'
Requires-Dist: leidenalg; extra == 'dev'
Requires-Dist: louvain; extra == 'dev'
Requires-Dist: pre-commit>=2.7.1; extra == 'dev'
Requires-Dist: pytest>=4.4; extra == 'dev'
Provides-Extra: docs
Requires-Dist: ipykernel; extra == 'docs'
Requires-Dist: ipython; extra == 'docs'
Requires-Dist: myst-nb; extra == 'docs'
Requires-Dist: scanpydoc[typehints]>=0.7.4; extra == 'docs'
Requires-Dist: sphinx-book-theme>=1.0; extra == 'docs'
Requires-Dist: sphinx-copybutton; extra == 'docs'
Requires-Dist: sphinx>=4; extra == 'docs'
Requires-Dist: sphinxcontrib-bibtex>=1.0.0; extra == 'docs'
Requires-Dist: sphinxext-opengraph; extra == 'docs'
